{
  "name": "SP-404 Live",
  "description": "SP-404 MK2 centered setup. Pads trigger synths, KeyLab for melodic parts.",
  "routes": [
    {
      "from": "SP-404 MK2",
      "to": "Behringer Model D",
      "filter": { "channels": [1], "message_types": ["note"] }
    },
    {
      "from": "SP-404 MK2",
      "to": "MS-20 Mini",
      "filter": { "channels": [2], "message_types": ["note"] }
    },
    {
      "from": "SP-404 MK2",
      "to": "Volca 1",
      "filter": { "channels": [3], "message_types": ["note"] }
    },
    {
      "from": "SP-404 MK2",
      "to": "Volca 2",
      "filter": { "channels": [4], "message_types": ["note"] }
    },
    {
      "from": "SP-404 MK2",
      "to": "Volca 3",
      "filter": { "channels": [5], "message_types": ["note"] }
    },
    {
      "from": "KeyLab 88 MK2",
      "to": "Roland JP-08",
      "filter": { "channels": [6] }
    },
    {
      "from": "KeyLab 88 MK2",
      "to": "MicroBrute",
      "filter": { "channels": [7] }
    }
  ],
  "clock_source": "SP-404 MK2"
}
